Doraemon/__init__.py
Doraemon/run.py
Doraemon/Crawlers/QQmusic_spider_by_album.py
Doraemon/Crawlers/QQmusic_spider_by_area.py
Doraemon/Crawlers/__init__.py
Doraemon/Crawlers/dianping.py
Doraemon/Crawlers/google_KG.py
Doraemon/Crawlers/google_translator.py
Doraemon/Crawlers/investigation.py
Doraemon/Crawlers/ocr_dora.py
Doraemon/Crawlers/qq_music_crawler_by_album.py
Doraemon/Crawlers/qq_music_crawler_by_area.py
Doraemon/Crawlers/whois.py
Doraemon/Crawlers_scrapy/__init__.py
Doraemon/MySQL/__init__.py
Doraemon/MySQL/mysql.py
Doraemon/MySQL/poi.py
Doraemon/MySQL/settings.py
Doraemon/OnlineSearch/__init__.py
Doraemon/OnlineSearch/dianping.py
Doraemon/OnlineSearch/google_KG.py
Doraemon/OnlineSearch/google_translator.py
Doraemon/OnlineSearch/whois.py
Doraemon/Others/__init__.py
Doraemon/Others/domain2ip.py
Doraemon/Others/ext_apis.py
Doraemon/Others/logging_dora.py
Doraemon/Requests/__init__.py
Doraemon/Requests/chrome_dora.py
Doraemon/Requests/proxies_dora.py
Doraemon/Requests/requests_dora.py
Doraemon/Requests/settings.py
Doraemon/WeiboRobot/__init__.py
Doraemon/WeiboRobot/weibo_robot.py
Doraemon-4.7.dist-info/LICENSE.txt
Doraemon-4.7.dist-info/METADATA
Doraemon-4.7.dist-info/WHEEL
Doraemon-4.7.dist-info/top_level.txt
Doraemon-4.7.dist-info/RECORD
