Metadata-Version: 2.1
Name: Doraemon
Version: 4.7
Summary: The pocket of Doraemon: many tools
Home-page: https://github.com/131250208/Doraemon
Author: Andy Wong
Author-email: wangyucheng@iie.ac.cn
License: MIT
Platform: UNKNOWN
Classifier: License :: OSI Approved :: MIT License
Classifier: Programming Language :: Python
Classifier: Programming Language :: Python :: 3
Classifier: Programming Language :: Python :: 3.6
Classifier: Programming Language :: Python :: Implementation :: CPython
Classifier: Programming Language :: Python :: Implementation :: PyPy
Requires-Python: >=3.5.0
Requires-Dist: selenium
Requires-Dist: requests
Requires-Dist: bs4
Requires-Dist: chardet (<4.0,>=2.0)
Requires-Dist: aiohttp
Requires-Dist: tqdm
Requires-Dist: rsa
Requires-Dist: webdriver-manager
Requires-Dist: PyExecJS
Requires-Dist: nest-asyncio
